[
  {
    "lat": -12.0291192,
    "lng": -76.9243711,
    "title": "Tagore"
  },
  {
    "lat": -12.034984,
    "lng": -76.929252,
    "title": "Los Angeles"
  },
  {
    "lat": -12.03622,
    "lng": -76.930352,
    "title": "Soldadura"
  },
  {
    "lat": -12.037592,
    "lng": -76.931488,
    "title": "Vista Alegre"
  },
  {
    "lat": -12.04134,
    "lng": -76.934706,
    "title": "Pista Nueva "
  },
  {
    "lat": -12.043681,
    "lng": -76.937677,
    "title": "Josfel "
  },
  {
    "lat": -12.047243,
    "lng": -76.938185,
    "title": "Backus"
  },
  {
    "lat": -12.052147,
    "lng": -76.940941,
    "title": "Mayorazgo"
  },
  {
    "lat": -12.053617,
    "lng": -76.941735,
    "title": "Separadora Industrial"
  },
  {
    "lat": -12.056505,
    "lng": -76.944329,
    "title": "Huarochirí"
  },
  {
    "lat": -12.060587,
    "lng": -76.942451,
    "title": "Constructores"
  },
  {
    "lat": -12.062534,
    "lng": -76.945996,
    "title": "Flora Tristán"
  },
  {
    "lat": -12.062999,
    "lng": -76.950761,
    "title": "Ingenieros"
  },
  {
    "lat": -12.065885,
    "lng": -76.954916,
    "title": "Industriales"
  },
  {
    "lat": -12.067662,
    "lng": -76.958281,
    "title": "La Molina "
  },
  {
    "lat": -12.071139,
    "lng": -76.956935,
    "title": "Javier Prado"
  },
  {
    "lat": -12.075137,
    "lng": -76.96342,
    "title": "Los Frutales"
  },
  {
    "lat": -12.07977431371267,
    "lng": -76.96596803347985,
    "title": "Camacho"
  },
  {
    "lat": -12.08224090410187,
    "lng": -76.96870521950441,
    "title": "Clínica"
  },
  {
    "lat": -12.08361968866327,
    "lng": -76.97268281134174,
    "title": "La Floresta"
  },
  {
    "lat": -12.08459339383542,
    "lng": -76.98036497443009,
    "title": "Evitamiento"
  },
  {
    "lat": -12.08511979577778,
    "lng": -76.9859328217407,
    "title": "Circunvalación"
  },
  {
    "lat": -12.08589138943128,
    "lng": -76.98920149041378,
    "title": "J. Borja"
  },
  {
    "lat": -12.086843339883293,
    "lng": -76.99284910503054,
    "title": "Rosa Toro"
  },
  {
    "lat": -12.087376559180079,
    "lng": -76.99686947747074,
    "title": "San Luis"
  },
  {
    "lat": -12.088477218717058,
    "lng": -77.00459021524178,
    "title": "Aviación"
  },
  {
    "lat": -12.088978629510029,
    "lng": -77.00802929699455,
    "title": "Guardia Civil"
  },
  {
    "lat": -12.089624982034449,
    "lng": -77.01580069225925,
    "title": "Quiñones"
  },
  {
    "lat": -12.091337704729257,
    "lng": -77.0262335473476,
    "title": "Masías"
  },
  {
    "lat": -12.091444444303741,
    "lng": -77.02804006030448,
    "title": "Orquídeas"
  },
  {
    "lat": -12.0919837,
    "lng": -77.0325634,
    "title": "Petit Thouars"
  },
  {
    "lat": -12.0921988,
    "lng": -77.03457,
    "title": "Arenales"
  },
  {
    "lat": -12.0932238,
    "lng": -77.0396058,
    "title": "Las Palmeras"
  },
  {
    "lat": -12.0938125,
    "lng": -77.0452647,
    "title": "Los Nogales"
  },
  {
    "lat": -12.0944958,
    "lng": -77.0499482,
    "title": "Pershing"
  },
  {
    "lat": -12.0929711,
    "lng": -77.0536806,
    "title": "Salaverry"
  },
  {
    "lat": -12.0900152,
    "lng": -77.0579872,
    "title": "Gregorio Escobedo"
  },
  {
    "lat": -12.087825443994566,
    "lng": -77.06129738912824,
    "title": "Hospital Militar"
  },
  {
    "lat": -12.083009721974847,
    "lng": -77.0675890947066,
    "title": "Sucre"
  },
  {
    "lat": -12.08087857079425,
    "lng": -77.0736654254652,
    "title": "Bartolomé Herrera"
  },
  {
    "lat": -12.078484680907048,
    "lng": -77.08112456360301,
    "title": "La Marina"
  },
  {
    "lat": -12.074554269732277,
    "lng": -77.07965433699786,
    "title": "La Mar"
  },
  {
    "lat": -12.067775369078557,
    "lng": -77.07796451741183,
    "title": "Católica"
  },
  {
    "lat": -12.061814653303449,
    "lng": -77.07899764714115,
    "title": "San Marcos"
  }
]